Metadata-Version: 2.4
Name: rc-tidevice3
Version: 0.1.6
Summary: forked from codeskyblue/tidevice3, wrapper for pymobiledevice3 for easy use with iphone device
Project-URL: Homepage, https://github.com/mthorta001/tidevice3
Project-URL: Repository, https://github.com/mthorta001/tidevice3
Project-URL: Documentation, https://github.com/mthorta001/tidevice3#readme
Project-URL: Issues, https://github.com/mthorta001/tidevice3/issues
Project-URL: Changelog, https://github.com/mthorta001/tidevice3/releases
Author-email: mthorta001 <mthorta001@gmail.com>
Maintainer-email: mthorta001 <mthorta001@gmail.com>
License: MIT
License-File: LICENSE
Keywords: automation,device,ios,iphone,mobile,pymobiledevice3,testing
Classifier: Development Status :: 4 - Beta
Classifier: Intended Audience :: Developers
Classifier: License :: OSI Approved :: MIT License
Classifier: Operating System :: OS Independent
Classifier: Programming Language :: Python :: 3
Classifier: Programming Language :: Python :: 3.8
Classifier: Programming Language :: Python :: 3.9
Classifier: Programming Language :: Python :: 3.10
Classifier: Programming Language :: Python :: 3.11
Classifier: Programming Language :: Python :: 3.12
Classifier: Topic :: Software Development :: Testing
Classifier: Topic :: System :: Hardware :: Hardware Drivers
Classifier: Topic :: Utilities
Requires-Python: >=3.8
Requires-Dist: click
Requires-Dist: fastapi
Requires-Dist: imageio[ffmpeg]>=2.33.1
Requires-Dist: numpy
Requires-Dist: pillow>=10.0
Requires-Dist: pydantic>=2.5.3
Requires-Dist: pymobiledevice3>=4.2.3
Requires-Dist: requests
Requires-Dist: zeroconf>=0.132.2
Provides-Extra: dev
Requires-Dist: isort>=5.13.2; extra == 'dev'
Requires-Dist: pytest-cov>=4.1.0; extra == 'dev'
Requires-Dist: pytest-httpserver>=1.0.8; extra == 'dev'
Requires-Dist: pytest>=7.4.4; extra == 'dev'
